sense_hat_display_utils/__init__.py
sense_hat_display_utils/__main__.py
sense_hat_display_utils/icons.py
sense_hat_display_utils/utility.py
sense_hat_display_utils-0.1.6.dist-info/DESCRIPTION.rst
sense_hat_display_utils-0.1.6.dist-info/METADATA
sense_hat_display_utils-0.1.6.dist-info/RECORD
sense_hat_display_utils-0.1.6.dist-info/WHEEL
sense_hat_display_utils-0.1.6.dist-info/entry_points.txt
sense_hat_display_utils-0.1.6.dist-info/metadata.json
sense_hat_display_utils-0.1.6.dist-info/top_level.txt
