Metadata-Version: 2.0
Name: sense-hat-display-utils
Version: 0.1.6
Summary: Utilities for the LED display on the Raspberry Pi Sense HAT
Home-page: https://github.com/e2m4n/python-sense-hat-display-utils
Author: Aaron Fleming
Author-email: e_z_a@hotmail.com
License: UNKNOWN
Keywords: sense-hat
Platform: UNKNOWN
Classifier: Development Status :: 4 - Beta
Classifier: Intended Audience :: Developers
Classifier: Programming Language :: Python :: 3
Requires-Dist: sense-hat
Requires-Dist: Pillow
Requires-Dist: colour
